pythonforwindows-1.0.4.dist-info/licenses/AUTHORS
pythonforwindows-1.0.4.dist-info/licenses/LICENSE
windows/__init__.py
windows/alpc.py
windows/com.py
windows/dbgprint.py
windows/hooks.py
windows/injection.py
windows/pe_parse.py
windows/pipe.py
windows/pycompat.py
windows/remotectypes.py
windows/security.py
windows/syswow64.py
windows/test.py
windows/wintrust.py
windows/crypto/__init__.py
windows/crypto/binary_string_conversion.py
windows/crypto/catalog.py
windows/crypto/certificate.py
windows/crypto/cryptmsg.py
windows/crypto/dpapi.py
windows/crypto/encrypt_decrypt.py
windows/crypto/generation.py
windows/crypto/sign_verify.py
windows/debug/__init__.py
windows/debug/breakpoints.py
windows/debug/debugger.py
windows/debug/localdbg.py
windows/debug/symboldbg.py
windows/debug/symbols.py
windows/generated_def/__init__.py
windows/generated_def/auto_doc_tst.py
windows/generated_def/flag.py
windows/generated_def/interfaces.py
windows/generated_def/meta.py
windows/generated_def/ntstatus.py
windows/generated_def/windef.py
windows/generated_def/winerror.py
windows/generated_def/winfuncs.py
windows/generated_def/winstructs.py
windows/native_exec/__init__.py
windows/native_exec/cpuid.py
windows/native_exec/native_function.py
windows/native_exec/nativeutils.py
windows/native_exec/simple_arm64.py
windows/native_exec/simple_x64.py
windows/native_exec/simple_x86.py
windows/rpc/__init__.py
windows/rpc/client.py
windows/rpc/epmapper.py
windows/rpc/ndr.py
windows/rpc/stubborn.py
windows/utils/__init__.py
windows/utils/improved_buffer.py
windows/utils/pythonutils.py
windows/utils/winutils.py
windows/winobject/__init__.py
windows/winobject/apisetmap.py
windows/winobject/bits.py
windows/winobject/device_manager.py
windows/winobject/event_log.py
windows/winobject/event_trace.py
windows/winobject/exception.py
windows/winobject/file.py
windows/winobject/handle.py
windows/winobject/hyperv.py
windows/winobject/network.py
windows/winobject/object_manager.py
windows/winobject/process.py
windows/winobject/registry.py
windows/winobject/service.py
windows/winobject/system.py
pythonforwindows-1.0.4.dist-info/METADATA
pythonforwindows-1.0.4.dist-info/WHEEL
pythonforwindows-1.0.4.dist-info/top_level.txt
pythonforwindows-1.0.4.dist-info/RECORD
