Metadata-Version: 2.4
Name: PythonForWindows
Version: 1.0.4
Summary: A codebase aimed to make interaction with Windows and native execution easier
Home-page: https://github.com/hakril/PythonForWindows
Author: Hakril
Author-email: pfw@hakril.net
License: BSD
Keywords: windows python
Classifier: Programming Language :: Python :: 3
Classifier: Programming Language :: Python :: 2.7
License-File: LICENSE
License-File: AUTHORS
Dynamic: author
Dynamic: author-email
Dynamic: classifier
Dynamic: description
Dynamic: description-content-type
Dynamic: home-page
Dynamic: keywords
Dynamic: license
Dynamic: license-file
Dynamic: summary
